{
  "name": "Leather Armor",
  "id": 9950,
  "content": "The breastplate and shoulder protectors of this armor are made of leather that has been stiffened by being boiled in oil. The rest of the armor is made of softer and more flexible materials.\n\n",
  "htmlcontent": "The breastplate and shoulder protectors of this armor are made of leather that has been stiffened by being boiled in oil. The rest of the armor is made of softer and more flexible materials.<br><br>",
  "data": {
    "AC": "11",
    "Source": "SRD 5.0",
    "Weight": "10",
    "Category": "Items",
    "Item Type": "Light Armor"
  }
}